encrypted_session/__init__.py
gnucash_web/__init__.py
gnucash_web/auth.py
gnucash_web/book.py
gnucash_web/commodities.py
gnucash_web/version.txt
gnucash_web/wsgi.py
gnucash_web/config/__init__.py
gnucash_web/config/default.py
gnucash_web/static/gnucash-web.css
gnucash_web/static/gnucash-web.js
gnucash_web/static/jquery-3.6.1.min.js
gnucash_web/static/bootstrap/css/bootstrap-grid.min.css
gnucash_web/static/bootstrap/css/bootstrap-grid.rtl.min.css
gnucash_web/static/bootstrap/css/bootstrap-reboot.min.css
gnucash_web/static/bootstrap/css/bootstrap-reboot.rtl.min.css
gnucash_web/static/bootstrap/css/bootstrap-utilities.min.css
gnucash_web/static/bootstrap/css/bootstrap-utilities.rtl.min.css
gnucash_web/static/bootstrap/css/bootstrap.min.css
gnucash_web/static/bootstrap/css/bootstrap.rtl.min.css
gnucash_web/static/bootstrap/js/bootstrap.bundle.min.js
gnucash_web/static/bootstrap/js/bootstrap.esm.min.js
gnucash_web/static/bootstrap/js/bootstrap.min.js
gnucash_web/static/bootstrap-icon-font/bootstrap-icons.css
gnucash_web/static/bootstrap-icon-font/fonts/bootstrap-icons.woff
gnucash_web/static/bootstrap-icon-font/fonts/bootstrap-icons.woff2
gnucash_web/static/img/official/128x128/apps/gnucash-icon.png
gnucash_web/static/img/official/16x16/apps/gnucash-icon.png
gnucash_web/static/img/official/22x22/apps/gnucash-icon.png
gnucash_web/static/img/official/24x24/apps/gnucash-icon.png
gnucash_web/static/img/official/256x256/apps/gnucash-icon.png
gnucash_web/static/img/official/32x32/apps/gnucash-icon.png
gnucash_web/static/img/official/48x48/apps/gnucash-icon.png
gnucash_web/static/img/official/64x64/apps/gnucash-icon.png
gnucash_web/static/img/official/96x96/apps/gnucash-icon.png
gnucash_web/static/img/official/scalable/apps/gnucash-icon.svg
gnucash_web/static/selectize/css/selectize.bootstrap2.css
gnucash_web/static/selectize/css/selectize.bootstrap3.css
gnucash_web/static/selectize/css/selectize.bootstrap4.css
gnucash_web/static/selectize/css/selectize.bootstrap5.css
gnucash_web-0.1.4.dist-info/METADATA
gnucash_web-0.1.4.dist-info/WHEEL
gnucash_web-0.1.4.dist-info/entry_points.txt
gnucash_web-0.1.4.dist-info/top_level.txt
gnucash_web-0.1.4.dist-info/RECORD
