Metadata-Version: 2.1
Name: gnucash_web
Version: 0.1.4
Summary: A simple, easy to use, mobile-friendly webinterface for GnuCash intended for self-hosting
Home-page: https://github.com/joshuabach/gnucash-web
Author: Joshua Bachmeier
Author-email: joshua@bachmeier.cc
License: GPLv3+
Project-URL: Bug Tracker, https://github.com/joshuabach/gnucash-web/issues
Project-URL: Source Code, https://github.com/joshuabach/gnucash-web
Keywords: bootstrap,flask,web,gnucash
Classifier: Development Status :: 4 - Beta
Classifier: Environment :: Web Environment
Classifier: Framework :: Flask
Classifier: Intended Audience :: Financial and Insurance Industry
Classifier: Intended Audience :: Information Technology
Classifier: License :: OSI Approved :: GNU General Public License v3 or later (GPLv3+)
Classifier: Natural Language :: English
Classifier: Operating System :: OS Independent
Classifier: Programming Language :: Python :: 3 :: Only
Classifier: Programming Language :: Python :: 3.8
Classifier: Topic :: Internet :: WWW/HTTP :: WSGI :: Application
Requires-Python: >=3.8,<3.12
Requires-Dist: Flask <2.3.0,>=2.0.2
Requires-Dist: Werkzeug <3.0.0
Requires-Dist: piecash >=1.2.0
Requires-Dist: pycryptodome >=3.12.0
Requires-Dist: babel >=2.9.1
Requires-Dist: requests >=2.27.1
Provides-Extra: mysql
Requires-Dist: mysql ; extra == 'mysql'
Provides-Extra: pgsql
Requires-Dist: psycopg2 ; extra == 'pgsql'
